odoo/addons/community_maps/__init__.py
odoo/addons/community_maps/__manifest__.py
odoo/addons/community_maps/controllers/__init__.py
odoo/addons/community_maps/controllers/cm_map_controller.py
odoo/addons/community_maps/models/__init__.py
odoo/addons/community_maps/models/cm_crowdfunding_notification.py
odoo/addons/community_maps/models/cm_crowdfunding_notification_request.py
odoo/addons/community_maps/models/cm_filter.py
odoo/addons/community_maps/models/cm_filter_group.py
odoo/addons/community_maps/models/cm_form_model.py
odoo/addons/community_maps/models/cm_form_submission.py
odoo/addons/community_maps/models/cm_form_submission_metadata.py
odoo/addons/community_maps/models/cm_map.py
odoo/addons/community_maps/models/cm_map_colorschema.py
odoo/addons/community_maps/models/cm_metadata.py
odoo/addons/community_maps/models/cm_partner.py
odoo/addons/community_maps/models/cm_place.py
odoo/addons/community_maps/models/cm_place_category.py
odoo/addons/community_maps/models/cm_place_presenter_metadata.py
odoo/addons/community_maps/models/cm_presenter_model.py
odoo/addons/community_maps/models/cm_slug_id_mixin.py
odoo/addons/community_maps/models/cm_utils.py
odoo/addons/community_maps/security/ir.model.access.csv
odoo/addons/community_maps/services/__init__.py
odoo/addons/community_maps/services/cm_map_service.py
odoo/addons/community_maps/services/cm_ping_service.py
odoo/addons/community_maps/static/src/img/community_maps_odoo_icon.png
odoo/addons/community_maps/views/cm_filter_group.xml
odoo/addons/community_maps/views/cm_form_model.xml
odoo/addons/community_maps/views/cm_form_submission.xml
odoo/addons/community_maps/views/cm_map.xml
odoo/addons/community_maps/views/cm_map_colorschema.xml
odoo/addons/community_maps/views/cm_menu_root.xml
odoo/addons/community_maps/views/cm_menu_root_config.xml
odoo/addons/community_maps/views/cm_place.xml
odoo/addons/community_maps/views/cm_place_category.xml
odoo/addons/community_maps/views/cm_place_presenter_metadata.xml
odoo12_addon_community_maps-12.0.0.2.10.dist-info/METADATA
odoo12_addon_community_maps-12.0.0.2.10.dist-info/WHEEL
odoo12_addon_community_maps-12.0.0.2.10.dist-info/top_level.txt
odoo12_addon_community_maps-12.0.0.2.10.dist-info/RECORD
