Metadata-Version: 2.1
Name: odoo12-addon-community-maps
Version: 12.0.0.2.10
Summary: Module to create and manage your map visualizations into a website
Home-page: https://gitlab.com/coopdevs/community-maps-builder-backend
Author: Coopdevs Treball SCCL
License: UNKNOWN
Platform: UNKNOWN
Classifier: Programming Language :: Python
Classifier: Framework :: Odoo
Classifier: Framework :: Odoo :: 12.0
Requires-Python: >=3.5
Requires-Dist: odoo12-addon-base-rest
Requires-Dist: odoo12-addon-base-rest-base-structure
Requires-Dist: odoo12-addon-base-rest-datamodel
Requires-Dist: odoo <12.1dev,>=12.0a
